MANIFEST.in
README.md
README.rst
setup.py
yandexwebdav.py
ydw.py
yandexwebdav.egg-info/PKG-INFO
yandexwebdav.egg-info/SOURCES.txt
yandexwebdav.egg-info/dependency_links.txt
yandexwebdav.egg-info/requires.txt
yandexwebdav.egg-info/top_level.txt