Metadata-Version: 1.0
Name: yandexwebdav
Version: 0.2.10
Summary: Simple wrapper to work with yandex disk using webdav Basic Auth
Home-page: https://github.com/lexich/yandex-disk-webdav
Author: lexich
Author-email: lexich121@gmail.com
License: MIT
Platform: UNKNOWN
